pyxstr2swift/__init__.py
pyxstr2swift/xstr2swift.py
pyxstr2swift-0.1.0.dist-info/METADATA
pyxstr2swift-0.1.0.dist-info/RECORD
pyxstr2swift-0.1.0.dist-info/WHEEL
pyxstr2swift-0.1.0.dist-info/entry_points.txt
pyxstr2swift-0.1.0.dist-info/top_level.txt
