Metadata-Version: 2.1
Name: pyxstr2swift
Version: 0.1.0
Summary: Python package for a xcode strings file to a swift localized string file
Home-page: https://github.com/ocworld/pyxstr2swift
Author: Keunhyun Oh
Author-email: ocworld@gmail.com
License: MIT License
